Sem3/DDCO_lab/lab2/circuit1.v
module circuit1 (A, B, C, D);
  output D;
  input A, B, C;
  wire bottom_wire;

  and G_bottom(bottom_wire, C, D);
  or G_top(D, bottom_wire, A); 
endmodule

Sem3/DDCO_lab/lab2/circuit1_tb.v
module circuit1_tb;
  reg A, B, C;
  wire D;

  circuit1 UUT (.A(A), .B(B), .C(C), .D(D));

  initial begin
    A = 0; B = 0; C = 0; #20
    A = 1; B = 0; C = 0; #20
    A = 0; B = 1; C = 0; #20
    A = 1; B = 1; C = 0; #20
    A = 0; B = 0; C = 1; #20
    A = 1; B = 0; C = 1; #20
    A = 0; B = 1; C = 1; #20
    A = 1; B = 1; C = 1; 
  end

  initial begin
    $monitor("Time: %d, A = %b, B = %b, C = %b, D = %b", $time, A, B, C, D);
  end

  initial begin
    $dumpfile("circuit1.vcd");
    $dumpvars(0, circuit1_tb);
  end
endmodule

Sem3/DDCO_lab/lab2/circuit1.vcd
$date
	Fri Aug 25 10:04:20 2023
$end
$version
	Icarus Verilog
$end
$timescale
	1s
$end
$scope module circuit1_tb $end
$var wire 1 ! D $end
$var reg 1 " A $end
$var reg 1 # B $end
$var reg 1 $ C $end
$scope module UUT $end
$var wire 1 " A $end
$var wire 1 # B $end
$var wire 1 $ C $end
$var wire 1 ! D $end
$var wire 1 % bottom_wire $end
$upscope $end
$upscope $end
$enddefinitions $end
$comment Show the parameter values. $end
$dumpall
$end
#0
$dumpvars
0%
0$
0#
0"
0!
$end
#20
1!
1"
#40
0!
1#
0"
#60
1!
1"
#80
0!
1$
0#
0"
#100
1%
1!
1"
#120
1#
0"
#140
1"
