Sem3/DDCO_lab/lab2/circuit2.v
module circuit2(
    input A2, B2, C2,
    output Y
);

assign Y = (A2 | (C2 & B2)) | (B2 & A2);

endmodule

Sem3/DDCO_lab/lab2/circuit2_tb.v
module circuit2_tb;
  reg A2, B2, C2;
  wire Y;

  circuit2 UUT (.A2(A2), .B2(B2), .C2(C2), .Y(Y));

  initial begin
    A2 = 0; B2 = 0; C2 = 0; #20;
    A2 = 1; B2 = 0; C2 = 0; #20;
    A2 = 0; B2 = 1; C2 = 0; #20;
    A2 = 1; B2 = 1; C2 = 0; #20;
    A2 = 0; B2 = 0; C2 = 1; #20;
    A2 = 1; B2 = 0; C2 = 1; #20;
    A2 = 0; B2 = 1; C2 = 1; #20;
    A2 = 1; B2 = 1; C2 = 1; 
  end

  initial begin
    $monitor("Time: %0t, A2 = %b, B2 = %b, C2 = %b, Y = %b", $time, A2, B2, C2, Y);
  end

  initial begin
    $dumpfile("circuit2.vcd");
    $dumpvars(0, circuit2_tb);
  end
endmodule

Sem3/DDCO_lab/lab2/circuit2.vcd
$date
	Fri Aug 25 10:04:53 2023
$end
$version
	Icarus Verilog
$end
$timescale
	1s
$end
$scope module circuit2_tb $end
$var wire 1 ! Y $end
$var reg 1 " A2 $end
$var reg 1 # B2 $end
$var reg 1 $ C2 $end
$scope module UUT $end
$var wire 1 " A2 $end
$var wire 1 # B2 $end
$var wire 1 $ C2 $end
$var wire 1 ! Y $end
$upscope $end
$upscope $end
$enddefinitions $end
$comment Show the parameter values. $end
$dumpall
$end
#0
$dumpvars
0$
0#
0"
0!
$end
#20
1!
1"
#40
0!
1#
0"
#60
1!
1"
#80
0!
1$
0#
0"
#100
1!
1"
#120
1!
1#
0"
#140
1"
